smart_repository_manager_core/__init__.py
smart_repository_manager_core/core/__init__.py
smart_repository_manager_core/core/git_commands.py
smart_repository_manager_core/core/git_operations.py
smart_repository_manager_core/core/git_status.py
smart_repository_manager_core/core/models/__init__.py
smart_repository_manager_core/core/models/config.py
smart_repository_manager_core/core/models/repository.py
smart_repository_manager_core/core/models/ssh_models.py
smart_repository_manager_core/core/models/token.py
smart_repository_manager_core/core/models/user.py
smart_repository_manager_core/services/__init__.py
smart_repository_manager_core/services/config_service.py
smart_repository_manager_core/services/git_service.py
smart_repository_manager_core/services/github_service.py
smart_repository_manager_core/services/network_service.py
smart_repository_manager_core/services/ssh_service.py
smart_repository_manager_core/services/storage_service.py
smart_repository_manager_core/services/structure_service.py
smart_repository_manager_core/services/sync_service.py
smart_repository_manager_core/utils/__init__.py
smart_repository_manager_core/utils/file_ops.py
smart_repository_manager_core/utils/helpers.py
smart_repository_manager_core/utils/validators.py
smart_repository_manager_core-0.2.0.dist-info/licenses/LICENSE
smart_repository_manager_core-0.2.0.dist-info/METADATA
smart_repository_manager_core-0.2.0.dist-info/WHEEL
smart_repository_manager_core-0.2.0.dist-info/top_level.txt
smart_repository_manager_core-0.2.0.dist-info/RECORD
