Metadata-Version: 2.4
Name: smart-repository-manager-core
Version: 0.2.0
Summary: Smart Repository Manager Core - A Python library for managing Git repositories with intelligent synchronization, SSH configuration validation, and GitHub integration.
Author-email: Alexander Suvorov <smartlegiondev@gmail.com>
License-Expression: BSD-3-Clause
Project-URL: Homepage, https://github.com/smartlegionlab/smart-repository-manager-core
Classifier: Programming Language :: Python :: 3
Classifier: Programming Language :: Python :: 3.7
Classifier: Programming Language :: Python :: 3.8
Classifier: Programming Language :: Python :: 3.9
Classifier: Programming Language :: Python :: 3.10
Classifier: Programming Language :: Python :: 3.11
Classifier: Programming Language :: Python :: 3.12
Classifier: Operating System :: OS Independent
Requires-Python: >=3.6
License-File: LICENSE
Dynamic: license-file
